universal_tool_client/__init__.py
universal_tool_client-0.0.2.dist-info/METADATA
universal_tool_client-0.0.2.dist-info/WHEEL
universal_tool_client-0.0.2.dist-info/RECORD
